label_image/__init__.py
label_image/main.py
label_image/data/predefined_classes.txt
label_image/libs/__init__.py
label_image/libs/canvas.py
label_image/libs/colorDialog.py
label_image/libs/combobox.py
label_image/libs/constants.py
label_image/libs/create_ml_io.py
label_image/libs/default_label_combobox.py
label_image/libs/hashableQListWidgetItem.py
label_image/libs/labelDialog.py
label_image/libs/labelFile.py
label_image/libs/lightWidget.py
label_image/libs/pascal_voc_io.py
label_image/libs/resources.py
label_image/libs/settings.py
label_image/libs/shape.py
label_image/libs/stringBundle.py
label_image/libs/toolBar.py
label_image/libs/ustr.py
label_image/libs/utils.py
label_image/libs/yolo_io.py
label_image/libs/zoomWidget.py
label_image/resources/icons/app.icns
label_image/resources/icons/app.png
label_image/resources/icons/app.svg
label_image/resources/icons/cancel.png
label_image/resources/icons/close.png
label_image/resources/icons/color.png
label_image/resources/icons/color_line.png
label_image/resources/icons/copy.png
label_image/resources/icons/delete.png
label_image/resources/icons/done.png
label_image/resources/icons/done.svg
label_image/resources/icons/edit.png
label_image/resources/icons/expert1.png
label_image/resources/icons/expert2.png
label_image/resources/icons/eye.png
label_image/resources/icons/feBlend-icon.png
label_image/resources/icons/file.png
label_image/resources/icons/fit-width.png
label_image/resources/icons/fit-window.png
label_image/resources/icons/fit.png
label_image/resources/icons/format_createml.png
label_image/resources/icons/format_voc.png
label_image/resources/icons/format_yolo.png
label_image/resources/icons/help.png
label_image/resources/icons/labels.png
label_image/resources/icons/labels.svg
label_image/resources/icons/light_brighten.svg
label_image/resources/icons/light_darken.png
label_image/resources/icons/light_darken.svg
label_image/resources/icons/light_lighten.png
label_image/resources/icons/light_reset.png
label_image-0.0.4.dist-info/LICENSE
label_image-0.0.4.dist-info/METADATA
label_image-0.0.4.dist-info/WHEEL
label_image-0.0.4.dist-info/entry_points.txt
label_image-0.0.4.dist-info/top_level.txt
label_image-0.0.4.dist-info/RECORD
